{
    "identifiers": [
        "UnityEngine",
        "Collections",
        "MonoBehaviour",
        "playing",
        "Input",
        "GetMouseButton",
        "Input",
        "GetAxis",
        "Input",
        "GetAxis",
        "playerCamera",
        "transform",
        "localEulerAngles",
        "y",
        "Input",
        "GetAxis",
        "playerCamera",
        "transform",
        "localEulerAngles",
        "x",
        "Input",
        "GetAxis",
        "overHeadCamera",
        "enabled",
        "playerCamera",
        "enabled",
        "playerCamera",
        "transform",
        "position",
        "Vector3",
        "hAxis",
        "vAxis",
        "playerCamera",
        "transform",
        "localEulerAngles",
        "Vector3",
        "rotationY",
        "rotationX",
        "overHeadCamera",
        "enabled",
        "playerCamera",
        "enabled"
    ],
    "literals": [
        "\"Horizontal\"",
        "\"Vertical\"",
        "\"Mouse X\"",
        "\"Mouse Y\""
    ],
    "variables": [
        "Camera",
        "playerCamera",
        "Camera",
        "overHeadCamera",
        "cameraThrust",
        "playing",
        "turn",
        "hAxis",
        "vAxis",
        "rotationX",
        "rotationY"
    ],
    "comments": [
        "Swap camera",
        "Swap camera back"
    ],
    "docstrings": [
        "* cameraThrust;"
    ],
    "functions": [
        "Awake",
        "FixedUpdate"
    ],
    "classes": [
        "GameController"
    ]
}