{
    "identifiers": [
        "hawqal",
        "dal",
        "dao",
        "Database",
        "staticmethod",
        "open",
        "file_name",
        "encoding",
        "db",
        "Database",
        "file_name",
        "makeConnection",
        "database",
        "cursor",
        "cursor",
        "execute",
        "row",
        "data",
        "cities",
        "append",
        "row",
        "row",
        "cities"
    ],
    "literals": [
        "\"database/hawqalDB.sqlite\"",
        "'r'",
        "\"utf8\"",
        "f\"SELECT * FROM cities ORDER BY name ASC\""
    ],
    "variables": [
        "cities",
        "file_name",
        "database",
        "cursor",
        "data"
    ],
    "comments": [],
    "docstrings": [],
    "functions": [
        "getCities"
    ],
    "classes": [
        "City"
    ]
}