{
    "identifiers": [
        "Collections",
        "Generic",
        "Linq",
        "Text",
        "Threading",
        "Tasks",
        "SOLID",
        "IRemoteService",
        "ITvService",
        "IRemoteService",
        "ITvService",
        "tvService",
        "_tvService",
        "tvService",
        "_tvService",
        "TurnOn"
    ],
    "literals": [],
    "variables": [
        "ITvService",
        "_tvService"
    ],
    "comments": [],
    "docstrings": [],
    "functions": [
        "PressOnButton",
        "TurnOn",
        "RemoteService",
        "PressOnButton"
    ],
    "classes": [
        "DIP",
        "RemoteService"
    ]
}