{
    "identifiers": [
        "IO",
        "Xml",
        "ClosedXML",
        "Excel",
        "IO",
        "ClosedXML",
        "IO",
        "NUnit",
        "Framework",
        "ClosedXML",
        "Tests",
        "IO",
        "TestCase",
        "TestCase",
        "TestCase",
        "TestCase",
        "TestCase",
        "TestCase",
        "TestCase",
        "xmlText",
        "expectedValue",
        "CreateReader",
        "xmlText",
        "reader",
        "GetOptionalBool",
        "AttributeName",
        "Assert",
        "That",
        "readValue",
        "Is",
        "EqualTo",
        "expectedValue",
        "attributeValue",
        "XmlToEnumMapper",
        "mapper",
        "AttributeName",
        "attributeValue",
        "XmlReader",
        "Create",
        "StringReader",
        "xmlContext",
        "mapper",
        "XmlToEnumMapper",
        "Builder",
        "Build",
        "XmlTreeReader",
        "xmlReader",
        "mapper",
        "reader",
        "Open",
        "Empty",
        "reader"
    ],
    "literals": [
        "\"test\"",
        "\"true\"",
        "\"1\"",
        "\"false\"",
        "\"0\"",
        "\"some text\"",
        "\"TRUE\"",
        "\"FALSE\"",
        "\"element\""
    ],
    "variables": [
        "AttributeName",
        "reader",
        "readValue",
        "xmlContext",
        "xmlReader",
        "reader"
    ],
    "comments": [
        "Test various methods (including extension methods) that reader correctly reads the value of",
        "an attribute.",
        "</summary>",
        "xsd says case sensitive, for non-readable values return null"
    ],
    "docstrings": [
        "<summary>"
    ],
    "functions": [
        "GetOptionalBool_reads_xsd_compliant_bool_values",
        "XmlTreeReader",
        "CreateReader"
    ],
    "classes": [
        "XmlTreeReaderAttributesTests"
    ]
}