{
    "identifiers": [
        "Contenedor",
        "AltaDensidad",
        "localStorage",
        "guardado",
        "c",
        "todosContenedores",
        "Contenedor",
        "c",
        "c",
        "c",
        "listaContenedores",
        "localStorage",
        "todosContenedores",
        "referencia",
        "peso",
        "volumen",
        "todosContenedores",
        "c",
        "c",
        "referencia",
        "alert",
        "todosContenedores",
        "Contenedor",
        "referencia",
        "peso",
        "volumen",
        "guardaContenedor",
        "listaContenedores",
        "referencia",
        "peso",
        "volumen",
        "todosContenedores",
        "c",
        "c",
        "referencia",
        "contenedor",
        "alert",
        "contenedor",
        "nuevaReferencia",
        "contenedor",
        "nuevoPeso",
        "contenedor",
        "nuevoVolumen",
        "guardaContenedor",
        "listaContenedores",
        "tbody",
        "tr",
        "contenedor",
        "contenedor",
        "contenedor",
        "tbody",
        "tr",
        "muyDensos",
        "tbodyDenso",
        "todosContenedores",
        "contenedor",
        "contenedor",
        "contenedor",
        "densidad",
        "muyDensos",
        "AltaDensidad",
        "contenedor",
        "contenedor",
        "trmuyDensos",
        "contenedor",
        "contenedor",
        "loadContendor",
        "evento",
        "evento",
        "parseInt",
        "parseFloat",
        "annadirContenedor",
        "referencia",
        "peso",
        "volumen",
        "evento",
        "evento",
        "evento",
        "parseInt",
        "parseFloat",
        "annadirContenedor",
        "referencia",
        "pesoNuevo",
        "volumenNuevo",
        "evento",
        "calcularAltaDensidad"
    ],
    "literals": [
        "'./Logica'",
        "'./Logica'",
        "'contenedores'",
        "'contenedor'",
        "'Referencia duplicada'",
        "'No se ha encontrado el contenedor'",
        "'#tablacontenedores tbody'",
        "\"\"",
        "\"tr\"",
        "<td>${contenedor.referencia}</td><td>${contenedor.peso}</td><td>${contenedor.volumen}</td>",
        "'#muydensos tbody'",
        "\"\"",
        "'tr'",
        "<td>${contenedor.referencia}</td><td>${contenedor.densidad}</td>",
        "'load'",
        "'formAnnadir'",
        "'submit'",
        "'referencia'",
        "'peso'",
        "'volumen'",
        "'formModificar'",
        "'submit'",
        "'modReferencia'",
        "'modPeso'",
        "'modVolumen'",
        "'calcular'",
        "'click'"
    ],
    "variables": [
        "todosContenedores",
        "muyDensos",
        "guardado",
        "contenedor",
        "tbody",
        "tr",
        "tbodyDenso",
        "densidad",
        "trmuyDensos",
        "referencia",
        "peso",
        "volumen",
        "referencia",
        "pesoNuevo",
        "volumenNuevo"
    ],
    "comments": [],
    "docstrings": [],
    "functions": [
        "loadContendor",
        "guardaContenedor",
        "annadirContenedor",
        "modificarContenedor",
        "listaContenedores",
        "calcularAltaDensidad"
    ],
    "classes": []
}