{
    "identifiers": [
        "com",
        "ddd",
        "server",
        "keygenerator",
        "org",
        "springframework",
        "beans",
        "factory",
        "annotation",
        "Autowired",
        "org",
        "springframework",
        "boot",
        "CommandLineRunner",
        "org",
        "springframework",
        "stereotype",
        "Component",
        "com",
        "ddd",
        "server",
        "keygenerator",
        "commands",
        "DecodePublicKey",
        "com",
        "ddd",
        "server",
        "keygenerator",
        "commands",
        "GenerateKeys",
        "picocli",
        "CommandLine",
        "picocli",
        "CommandLine",
        "IFactory",
        "Component",
        "Autowired",
        "factory",
        "Autowired",
        "generateKeys",
        "Autowired",
        "decodePublicKey",
        "Override",
        "args",
        "command",
        "args",
        "length",
        "args",
        "command",
        "command",
        "equals",
        "generateKeys",
        "factory",
        "execute",
        "args",
        "command",
        "equals",
        "decodePublicKey",
        "factory",
        "execute",
        "args"
    ],
    "literals": [
        "\"generate-keys\"",
        "\"decode-pub-key\""
    ],
    "variables": [
        "factory",
        "generateKeys",
        "decodePublicKey",
        "args"
    ],
    "comments": [
        "run picocli impl"
    ],
    "docstrings": [],
    "functions": [
        "run"
    ],
    "classes": [
        "CLRunner"
    ]
}