{
    "identifiers": [
        "dolfin",
        "numpy",
        "np",
        "u",
        "A",
        "B",
        "n",
        "u",
        "value_rank",
        "len",
        "A",
        "len",
        "B",
        "np",
        "linalg",
        "norm",
        "A",
        "B",
        "n",
        "A",
        "t",
        "B",
        "A",
        "t",
        "np",
        "linspace",
        "n",
        "len",
        "A",
        "Mesh",
        "MeshEditor",
        "editor",
        "open",
        "mesh",
        "tdim",
        "gdim",
        "editor",
        "init_vertices",
        "n",
        "editor",
        "init_cells",
        "n",
        "vi",
        "v",
        "mesh_points",
        "editor",
        "add_vertex",
        "vi",
        "v",
        "ci",
        "n",
        "editor",
        "add_cell",
        "ci",
        "np",
        "array",
        "ci",
        "ci",
        "dtype",
        "editor",
        "close",
        "u",
        "function_space",
        "ufl_element",
        "elm",
        "family",
        "elm",
        "degree",
        "FunctionSpace",
        "mesh",
        "family",
        "degree",
        "interpolate",
        "u",
        "V",
        "assemble",
        "v",
        "dx",
        "UnitSquareMesh",
        "FunctionSpace",
        "mesh",
        "Expression",
        "domain",
        "mesh",
        "degree",
        "interpolate",
        "f",
        "Vh",
        "np",
        "array",
        "np",
        "array",
        "line_integral",
        "vh",
        "A",
        "B",
        "n",
        "abs",
        "ans",
        "ans0"
    ],
    "literals": [
        "'interval'",
        "'uintp'",
        "'CG'",
        "'x[0]+x[1]'",
        "'Error'"
    ],
    "variables": [
        "mesh_points",
        "tdim",
        "gdim",
        "mesh",
        "editor",
        "elm",
        "family",
        "degree",
        "V",
        "v",
        "mesh",
        "Vh",
        "f",
        "vh",
        "A",
        "B",
        "ans",
        "ans0"
    ],
    "comments": [
        "Mesh line for integration",
        "'triangle'?",
        "Setup funcion space"
    ],
    "docstrings": [
        "'''Integrate u over segment [A, B] partitioned into n elements'''"
    ],
    "functions": [
        "line_integral"
    ],
    "classes": []
}