{
    "identifiers": [
        "matrix",
        "rows",
        "matrix",
        "length",
        "rows",
        "curlen",
        "cols",
        "matrix",
        "length",
        "flag",
        "maxLen",
        "i",
        "i",
        "rows",
        "i",
        "j",
        "j",
        "cols",
        "j",
        "matrix",
        "i",
        "j",
        "curlen",
        "flag",
        "i",
        "curlen",
        "rows",
        "j",
        "curlen",
        "cols",
        "flag",
        "k",
        "i",
        "k",
        "i",
        "curlen",
        "k",
        "matrix",
        "k",
        "j",
        "curlen",
        "flag",
        "k",
        "j",
        "k",
        "j",
        "curlen",
        "k",
        "matrix",
        "i",
        "curlen",
        "k",
        "flag",
        "flag",
        "curlen",
        "maxLen",
        "max",
        "maxLen",
        "curlen",
        "maxLen",
        "maxLen"
    ],
    "literals": [],
    "variables": [],
    "comments": [
        "TC: O(mn)",
        "SC: O(1)",
        "[i+curlen] [j+curlen]"
    ],
    "docstrings": [],
    "functions": [
        "maximalSquare"
    ],
    "classes": [
        "Solution"
    ]
}