{
    "identifiers": [
        "Newtonsoft",
        "Helper",
        "Collections",
        "Newtonsoft",
        "Json",
        "Linq",
        "Newtonsoft",
        "Json",
        "Collections",
        "Generic",
        "Linq",
        "NLog",
        "LogManager",
        "GetCurrentClassLogger",
        "JObject",
        "@this",
        "JArray",
        "array",
        "keyNames",
        "keyName",
        "keyNames",
        "array",
        "SelectTokens",
        "Where",
        "t",
        "Value",
        "keyName",
        "ToList",
        "foundTokens",
        "Count",
        "foundTokens",
        "FirstOrDefault",
        "Parent",
        "Parent",
        "ToObject",
        "JObject",
        "foundTokens",
        "Count",
        "i",
        "i",
        "foundTokens",
        "ElementAtOrDefault",
        "i",
        "rawToken",
        "Parent",
        "Parent",
        "ToObject",
        "JObject",
        "firstToken",
        "Merge",
        "token",
        "rawToken",
        "Parent",
        "Parent",
        "Remove",
        "foundTokens",
        "Parent",
        "Parent",
        "Replace",
        "firstToken",
        "array",
        "ex",
        "logger",
        "ex"
    ],
    "literals": [
        "\"Array could not merge.\""
    ],
    "variables": [
        "Logger",
        "logger",
        "foundTokens",
        "firstToken",
        "i",
        "rawToken",
        "token"
    ],
    "comments": [],
    "docstrings": [],
    "functions": [
        "JArray",
        "MergeArray"
    ],
    "classes": [
        "JObjectExtensions"
    ]
}