{
    "identifiers": [
        "Kiota",
        "Builder",
        "CodeDOM",
        "Kiota",
        "Builder",
        "PathSegmenters",
        "Xunit",
        "Kiota",
        "Builder",
        "Tests",
        "PathSegmenters",
        "segmenter",
        "CSharpPathSegmenter",
        "Fact",
        "segmenter",
        "NormalizeFileName",
        "CodeClass",
        "Name",
        "Assert",
        "Equal",
        "fileName",
        "Fact",
        "longNamespace",
        "longNamespace",
        "longNamespace",
        "longNamespace",
        "segmenter",
        "NormalizeNamespaceSegment",
        "longNamespace",
        "Assert",
        "NotEqual",
        "longNamespace",
        "normalizedNamespace",
        "Assert",
        "Equal",
        "normalizedNamespace",
        "Length",
        "Fact",
        "rootDir",
        "Length",
        "CSharpPathSegmenter",
        "MaxFilePathLength",
        "longNamespace",
        "Length",
        "rootDir",
        "rootDir",
        "longNamespace",
        "rootDir",
        "segmenter",
        "NormalizePath",
        "longPathName",
        "Assert",
        "NotEqual",
        "longPathName",
        "normalizedPath",
        "Assert",
        "normalizedPath",
        "Length",
        "longPathName",
        "Length",
        "Assert",
        "normalizedPath",
        "Length",
        "CSharpPathSegmenter",
        "MaxFilePathLength"
    ],
    "literals": [
        "\"D:\\\\source\\\\repos\\\\kiota-sample\"",
        "\"client\"",
        "\"testClass\"",
        "\"TestClass\"",
        "\"ThisIsAVeryLongNamespaceNameThatShouldBeTruncatedAsItIsLongerThanTwoHundredAndFiftySixCharactersAccordingToWindows\"",
        "\"D:\\\\source\\\\repos\\\\kiota-sample\\\\Item\\\\ErpBOLaborSvc\\\\\"",
        "\"ThisIsAVeryLongNamespaceNameThatIsNotLongerThanTwoHundredAndFiftySixCharactersAccordingToWindows\""
    ],
    "variables": [
        "CSharpPathSegmenter",
        "segmenter",
        "fileName",
        "longNamespace",
        "normalizedNamespace",
        "rootDir",
        "longNamespace",
        "longPathName",
        "normalizedPath"
    ],
    "comments": [
        "the file name should be PascalCase",
        "make it more than 256",
        "shortened to sha256 length",
        "new path is shorter than the original",
        "new path is shorter than the max path length"
    ],
    "docstrings": [],
    "functions": [
        "CSharpPathSegmenterTests",
        "CSharpPathSegmenterGeneratesCorrectFileName",
        "CSharpPathSegmenterDoesNotGenerateNamespaceFoldersThatAreTooLong",
        "CSharpPathSegmenterDoesNotGeneratePathsThatAreTooLong"
    ],
    "classes": [
        "CSharpPathSegmenterTests"
    ]
}