{
    "identifiers": [
        "Collections",
        "Collections",
        "Generic",
        "UnityEngine",
        "MonoBehaviour",
        "Item",
        "Sprite",
        "inventoryMngr",
        "GetComponent",
        "Inventory",
        "craftableItems",
        "Length",
        "guiItems",
        "Length",
        "Debug",
        "LogError",
        "itemIdx",
        "CanCraftItem",
        "itemIdx",
        "inventoryMngr",
        "AddItem",
        "craftableItems",
        "itemIdx",
        "i",
        "craftableItems",
        "Length",
        "i",
        "CanCraftItem",
        "i",
        "name",
        "i",
        "craftableItems",
        "Length",
        "i",
        "craftableItems",
        "i",
        "name",
        "name",
        "found",
        "craftableItems",
        "i",
        "found",
        "itemIdx",
        "craftableItems",
        "itemIdx",
        "found",
        "found",
        "itemCost",
        "scrap",
        "inventoryMngr",
        "resources",
        "scrap",
        "found",
        "itemCost",
        "energy",
        "inventoryMngr",
        "resources",
        "energy",
        "found",
        "itemCost",
        "wire",
        "inventoryMngr",
        "resources",
        "wire"
    ],
    "literals": [
        "\"GUI Items and Craftable Items sizes do not match.\""
    ],
    "variables": [
        "craftableItems",
        "guiItems",
        "Inventory",
        "inventoryMngr",
        "i",
        "Item",
        "found",
        "i",
        "Item",
        "found"
    ],
    "comments": [
        "Crafting component used to craft items for the player",
        "Attach this to the Crafting GUI when available",
        "Array of items that can be crafted",
        "Used to reference the craftable items",
        "Use this for initialization",
        "Calls Inventory class AddItem() to craft the item",
        "TODO: Show that you are not able to craft item",
        "Play a sound?",
        "Updates the GUI to show all craftable items",
        "TODO: Set the item to be craftable in GUI",
        "Find an item by name",
        "Check to see if an item can be crafted",
        "If item is not found return false"
    ],
    "docstrings": [],
    "functions": [
        "Start",
        "CraftItem",
        "UpdateCraftable",
        "Item",
        "FindItemByName",
        "CanCraftItem"
    ],
    "classes": [
        "Crafting"
    ]
}