{
    "identifiers": [
        "Component",
        "EventEmitter",
        "Input",
        "Output",
        "Component",
        "require",
        "require",
        "Input",
        "Output",
        "EventEmitter",
        "index",
        "index"
    ],
    "literals": [
        "'@angular/core'",
        "'article-edit-extend'",
        "'./extend.html'",
        "'./extend.scss'"
    ],
    "variables": [],
    "comments": [
        "删除自定义配置项目",
        "增加自定义配置项目",
        "改变数据后emit事件"
    ],
    "docstrings": [],
    "functions": [
        "delExtendItem",
        "addExtendItem",
        "emitExtendData"
    ],
    "classes": [
        "ArticleEditExtend"
    ]
}