{
    "identifiers": [
        "Collections",
        "Generic",
        "Linq",
        "Text",
        "Threading",
        "Tasks",
        "CoordinateToolLibrary"
    ],
    "literals": [
        "\"COPY_ALL_COORDINATE_OUTPUTS\"",
        "\"SELECTSR\"",
        "\"SRSELECTED\"",
        "\"BROADCAST_COORDINATE_NEEDED\"",
        "\"ADD_NEW_OUTPUT_COORDINATE\"",
        "\"BROADCAST_COORDINATE_VALUES\"",
        "\"REQUEST_OUTPUT_UPDATE\""
    ],
    "variables": [
        "CopyAllCoordinateOutputs",
        "SelectSpatialReference",
        "SpatialReferenceSelected",
        "RequestCoordinateBroadcast",
        "AddNewOutputCoordinate",
        "BroadcastCoordinateValues",
        "RequestOutputUpdate"
    ],
    "comments": [],
    "docstrings": [],
    "functions": [],
    "classes": [
        "Constants"
    ]
}