{
    "identifiers": [
        "logo",
        "React",
        "BrowserRouter",
        "Router",
        "Route",
        "PostListPage",
        "PostDetailPage",
        "WritePostPage",
        "div",
        "Router",
        "Route",
        "PostListPage",
        "Route",
        "Route",
        "PostDetailPage",
        "Route",
        "Route",
        "WritePostPage",
        "Route",
        "Router",
        "div",
        "App"
    ],
    "literals": [
        "'./logo.svg'",
        "\"react\"",
        "\"react-router-dom\"",
        "'./App.css'",
        "\"./pages/PostListPage\"",
        "\"./pages/PostDetailPage\"",
        "\"./pages/WritePostPage\"",
        "\"App\"",
        "\"/\"",
        "\"/posts/:postId\"",
        "\"/write/posts\""
    ],
    "variables": [],
    "comments": [],
    "docstrings": [],
    "functions": [
        "App"
    ],
    "classes": []
}