{
    "identifiers": [
        "ar",
        "i",
        "i",
        "i",
        "i",
        "i",
        "i",
        "i"
    ],
    "literals": [],
    "variables": [],
    "comments": [
        "divident value when using divident operator",
        "when Numerator is less than denominator result= 0",
        "divident",
        "modulus operator it will print remainder",
        "for modulus when numerator is less than denominator result= numerator",
        "for modulus when numerator is less than denominator result= numerator"
    ],
    "docstrings": [],
    "functions": [
        "main"
    ],
    "classes": [
        "WhileEx3"
    ]
}