{
    "identifiers": [
        "Component",
        "OnInit",
        "Track",
        "WsPackage",
        "ServerCtrlService",
        "WebsocketHandler",
        "Component",
        "serverCtrlService",
        "WebsocketHandler",
        "track",
        "track",
        "track",
        "track",
        "id",
        "options",
        "posDateTime",
        "pos",
        "posDateTime",
        "total",
        "WsPackage",
        "WsPackage"
    ],
    "literals": [
        "'@angular/core'",
        "'./track'",
        "'./ws-package'",
        "'./server-ctrl.service'",
        "'./websocket-handler'",
        "'player'",
        "'/player.component.html'",
        "'./app.component.css'",
        "'play_arrow'",
        "'https://www.youtube.com/watch?v='",
        "''",
        "'https://i.ytimg.com/vi/'",
        "'/hqdefault.jpg'",
        "'2-digit'",
        "'2-digit'",
        "'en-US'",
        "'['",
        "'|'",
        "']'",
        "'playing'",
        "'patch'",
        "'player/control'",
        "'pause'",
        "'patch'",
        "'player/control'",
        "'play'"
    ],
    "variables": [
        "id",
        "pos",
        "total",
        "options",
        "posDateTime"
    ],
    "comments": [
        "FIXME pl0x"
    ],
    "docstrings": [],
    "functions": [
        "ngOnInit",
        "setCurrentTrack",
        "updateTrackProgress",
        "onPlayerMethod"
    ],
    "classes": [
        "PlayerComponent"
    ]
}