{
    "identifiers": [
        "Linq",
        "NUnit",
        "Framework",
        "Constraints",
        "Org",
        "XmlUnit",
        "Builder",
        "Org",
        "XmlUnit",
        "Diff",
        "Org",
        "XmlUnit",
        "Constraints",
        "Constraint",
        "Org",
        "XmlUnit",
        "Diff",
        "Diff",
        "DefaultComparisonFormatter",
        "control",
        "diffBuilder",
        "DiffBuilder",
        "Compare",
        "control",
        "control",
        "CompareConstraint",
        "control",
        "CheckForIdentical",
        "control",
        "CompareConstraint",
        "control",
        "CheckForSimilar",
        "diffBuilder",
        "CheckForSimilar",
        "checkFor",
        "ComparisonResult",
        "SIMILAR",
        "diffBuilder",
        "CheckForIdentical",
        "checkFor",
        "ComparisonResult",
        "EQUAL",
        "formatXml",
        "diffBuilder",
        "IgnoreWhitespace",
        "formatXml",
        "diffBuilder",
        "NormalizeWhitespace",
        "diffBuilder",
        "IgnoreComments",
        "INodeMatcher",
        "nodeMatcher",
        "diffBuilder",
        "WithNodeMatcher",
        "nodeMatcher",
        "DifferenceEvaluator",
        "differenceEvaluator",
        "diffBuilder",
        "WithDifferenceEvaluator",
        "differenceEvaluator",
        "ComparisonListener",
        "comparisonListeners",
        "diffBuilder",
        "WithComparisonListeners",
        "comparisonListeners",
        "ComparisonListener",
        "comparisonListeners",
        "diffBuilder",
        "WithDifferenceListeners",
        "comparisonListeners",
        "IComparisonFormatter",
        "comparisonFormatter",
        "comparisonFormatter",
        "comparisonFormatter",
        "o",
        "checkFor",
        "ComparisonResult",
        "EQUAL",
        "diffBuilder",
        "WithComparisonController",
        "ComparisonControllers",
        "StopWhenSimilar",
        "checkFor",
        "ComparisonResult",
        "SIMILAR",
        "diffBuilder",
        "WithComparisonController",
        "ComparisonControllers",
        "StopWhenDifferent",
        "diffResult",
        "diffBuilder",
        "WithTest",
        "o",
        "Build",
        "diffResult",
        "HasDifferences",
        "MessageWriter",
        "writer",
        "writer",
        "Write",
        "diffResult",
        "TestSource",
        "SystemId",
        "checkFor",
        "ComparisonResult",
        "EQUAL",
        "diffResult",
        "ControlSource",
        "SystemId",
        "MessageWriter",
        "writer",
        "diffResult",
        "Differences",
        "First",
        "Comparison",
        "writer",
        "WriteMessageLine",
        "comparisonFormatter",
        "GetDescription",
        "c",
        "diffResult",
        "TestSource",
        "SystemId",
        "diffResult",
        "ControlSource",
        "SystemId",
        "writer",
        "WriteMessageLine",
        "Format",
        "diffResult",
        "TestSource",
        "SystemId",
        "diffResult",
        "ControlSource",
        "SystemId",
        "writer",
        "DisplayDifferences",
        "GetDetails",
        "c",
        "ControlDetails",
        "c",
        "Type",
        "GetDetails",
        "c",
        "TestDetails",
        "c",
        "Type",
        "Comparison",
        "Detail",
        "detail",
        "ComparisonType",
        "comparisonFormatter",
        "GetDetails",
        "detail",
        "formatXml"
    ],
    "literals": [
        "\"{0} is {1} to {2}\"",
        "\"identical\"",
        "\"similar\"",
        "\"comparing {0} to {1}\""
    ],
    "variables": [
        "DiffBuilder",
        "diffBuilder",
        "ComparisonResult",
        "checkFor",
        "diffResult",
        "formatXml",
        "IComparisonFormatter",
        "comparisonFormatter",
        "Comparison",
        "c"
    ],
    "comments": [
        "This file is licensed to You under the Apache License, Version 2.0\n  (the \"License\"); you may not use this file except in compliance with\n  the License.  You may obtain a copy of the License at\n\n  http://www.apache.org/licenses/LICENSE-2.0\n\n  Unless required by applicable law or agreed to in writing, software\n  distributed under the License is distributed on an \"AS IS\" BASIS,\n  WITHOUT WARRANTIES OR CONDITIONS OF ANY KIND, either express or implied.\n  See the License for the specific language governing permissions and\n  limitations under the License.",
        "Constraint that compares two XML sources with each other.",
        "</summary>",
        "Create a CompareConstraint which compares the",
        "test-Object with the given control Object for identity.",
        "</summary>",
        "Create a CompareConstraint which compares the",
        "test-Object with the given control Object for similarity.",
        "</summary>",
        "<remarks>",
        "<para>",
        "Example for Similar: The XML node",
        "\"&lt;a&gt;Text&lt;/a&gt;\" and",
        "\"&lt;a&gt;&lt;![CDATA[Text]]&gt;&lt;/a&gt;\" are",
        "similar and the Test will not fail.",
        "</para>",
        "</remarks>",
        "Use a custom Formatter for the Error Messages. The defaultFormatter is DefaultComparisonFormatter.",
        "</summary>"
    ],
    "docstrings": [
        "<summary>",
        "<summary>",
        "<summary>",
        "<summary>"
    ],
    "functions": [
        "CompareConstraint",
        "CompareConstraint",
        "IsIdenticalTo",
        "CompareConstraint",
        "IsSimilarTo",
        "CompareConstraint",
        "CheckForSimilar",
        "CompareConstraint",
        "CheckForIdentical",
        "CompareConstraint",
        "IgnoreWhitespace",
        "CompareConstraint",
        "NormalizeWhitespace",
        "CompareConstraint",
        "IgnoreComments",
        "CompareConstraint",
        "WithNodeMatcher",
        "CompareConstraint",
        "WithDifferenceEvaluator",
        "CompareConstraint",
        "WithComparisonListeners",
        "CompareConstraint",
        "WithDifferenceListeners",
        "CompareConstraint",
        "WithComparisonFormatter",
        "Matches",
        "WriteDescriptionTo",
        "WriteMessageTo",
        "GetDetails"
    ],
    "classes": [
        "CompareConstraint"
    ]
}