{
    "identifiers": [],
    "literals": [
        "\"use strict\"",
        "\"ui\"",
        "<div id=\"notifications\"></div>\n    <div id=\"sidebarToggleContainer\">\n        <i id=\"sidebarToggle\"></i>\n    </div>\n    <div id=\"sidebar\">\n        <div id=\"controls\">\n            <div id=\"displaySelection\">\n                <button id=\"radioMap\" checked>Map</button>\n                <button id=\"radioData\">Data</button>\n            </div>\n            <div id=\"dateSelection\">\n                <button id=\"radioMonth\" checked>Past Month</button>\n                <button id=\"radioWeek\">Past Week</button>\n                <button id=\"radioDay\">Yesterday</button>\n            </div>\n            <div id=\"typeSelection\"></div>\n        </div>\n        <div id=\"dataArea\" class=\"hidden\">\n            <table id=\"dataTable\"></table>\n        </div>\n        <div id=\"footer\">&copy; 2017 University of Pittsburgh Computer Science Club.</div>\n    </div>",
        "\"undefined\""
    ],
    "variables": [],
    "comments": [],
    "docstrings": [],
    "functions": [],
    "classes": []
}