{
    "identifiers": [
        "Enum",
        "IntEnum",
        "random",
        "IntEnum",
        "Enum",
        "card_name",
        "card_numb",
        "card_suit",
        "card_value",
        "discard",
        "card_name",
        "card_numb",
        "card_suit",
        "card_value",
        "discard",
        "name",
        "name",
        "suit",
        "name",
        "output",
        "suit",
        "Suit",
        "card",
        "Card",
        "card",
        "value",
        "card",
        "value",
        "fullDeck",
        "append",
        "PlayingCard",
        "card",
        "card",
        "value",
        "suit",
        "cardValue",
        "shuffle",
        "fullDeck",
        "deck",
        "input",
        "randint",
        "len",
        "deck",
        "deck",
        "pop",
        "rand_card",
        "winnerFound",
        "createDeck",
        "input",
        "randint",
        "fullDeck",
        "cutDepth",
        "cutDeck",
        "fullDeck",
        "cutDepth",
        "p1cut",
        "numb",
        "p2cut",
        "numb",
        "p1cut",
        "textPlay",
        "p2cut",
        "textPlay",
        "input",
        "p1cut",
        "numb",
        "p2cut",
        "numb",
        "p1cut",
        "textPlay",
        "p2cut",
        "textPlay",
        "input",
        "p1cut",
        "textPlay",
        "p2cut",
        "textPlay",
        "input",
        "dealer",
        "fullDeck",
        "dealer",
        "i",
        "player1cards",
        "append",
        "partialDeck",
        "pop",
        "player2cards",
        "append",
        "partialDeck",
        "pop",
        "createDeck",
        "deal"
    ],
    "literals": [
        "'spades'",
        "'clubs'",
        "'hearts'",
        "'diamonds'",
        "\" \"",
        "\"Hit enter to cut the deck\"",
        "\"Cut and see who goes first\"",
        "\"Player 1 cut - \"",
        "\"Computer cut - \"",
        "\"You win!! Your turn to deal\"",
        "\"Player 1 cut - \"",
        "\"Computer cut - \"",
        "\"You loose! Computer goes first\"",
        "\"Player 1 cut - \"",
        "\"Computer cut - \"",
        "\"TIE! Draw again\""
    ],
    "variables": [
        "fullDeck",
        "partialDeck",
        "player1cards",
        "player2cards",
        "dealer",
        "ACE",
        "TWO",
        "THREE",
        "FOUR",
        "FIVE",
        "SIX",
        "SEVEN",
        "EIGHT",
        "NINE",
        "TEN",
        "JACK",
        "QUEEN",
        "KING",
        "SPADES",
        "CLUBS",
        "HEARTS",
        "DIAMONDS",
        "name",
        "numb",
        "suit",
        "value",
        "discard",
        "output",
        "cardValue",
        "cardValue",
        "rand_card",
        "winnerFound",
        "cutDepth",
        "p1cut",
        "p2cut",
        "dealer",
        "winnerFound",
        "dealer",
        "winnerFound",
        "winnerFound",
        "partialDeck",
        "dealer"
    ],
    "comments": [
        "# Card enum for cards",
        "# Suit Enum for cards",
        "# Class to hold card info",
        "# Draw single card from deck",
        "dealer =  cutToStart()"
    ],
    "docstrings": [],
    "functions": [
        "textPlay",
        "createDeck",
        "cutDeck",
        "cutToStart",
        "deal"
    ],
    "classes": [
        "Card",
        "Suit",
        "PlayingCard"
    ]
}