{
    "identifiers": [
        "createSlice",
        "PayloadAction",
        "createSlice",
        "state",
        "state",
        "state",
        "state",
        "state",
        "action",
        "state",
        "action",
        "core"
    ],
    "literals": [
        "'@reduxjs/toolkit'",
        "'REGISTER'",
        "'LOGIN'",
        "'LOGIN'",
        "'core'"
    ],
    "variables": [
        "initialState",
        "core"
    ],
    "comments": [],
    "docstrings": [],
    "functions": [
        "showAuthModal",
        "closeAuthModal",
        "changeAuthModalMode"
    ],
    "classes": []
}