{
    "identifiers": [
        "com",
        "ags",
        "dilip",
        "elementcollection",
        "java",
        "util",
        "Collection",
        "java",
        "util",
        "javax",
        "persistence",
        "ElementCollection",
        "javax",
        "persistence",
        "Entity",
        "javax",
        "persistence",
        "Id",
        "Entity",
        "Id",
        "id",
        "ElementCollection",
        "vacationBookings",
        "ElementCollection",
        "name",
        "vacationBookings",
        "vacationBookings",
        "vacationBookings",
        "vacationBookings",
        "name",
        "name",
        "name",
        "name"
    ],
    "literals": [],
    "variables": [
        "id",
        "vacationBookings",
        "name"
    ],
    "comments": [],
    "docstrings": [],
    "functions": [
        "getVacationBookings",
        "setVacationBookings",
        "getName",
        "setName"
    ],
    "classes": [
        "Employee"
    ]
}