{
    "identifiers": [
        "it",
        "iit",
        "describe",
        "ddescribe",
        "expect",
        "inject",
        "injectAsync",
        "TestComponentBuilder",
        "beforeEachProviders",
        "provide",
        "MyAudio",
        "describe",
        "beforeEachProviders",
        "it",
        "injectAsync",
        "TestComponentBuilder",
        "tcb",
        "tcb",
        "MyAudio",
        "fixture",
        "fixture"
    ],
    "literals": [
        "'angular2/testing'",
        "'angular2/core'",
        "'./my-audio'",
        "'MyAudio Component'",
        "'should ...'"
    ],
    "variables": [],
    "comments": [],
    "docstrings": [],
    "functions": [],
    "classes": []
}