{
    "identifiers": [
        "DecimalPipe",
        "AfterViewInit",
        "ChangeDetectionStrategy",
        "Component",
        "forwardRef",
        "HostBinding",
        "Input",
        "OnDestroy",
        "ViewChild",
        "AbstractControl",
        "ControlValueAccessor",
        "NG_VALIDATORS",
        "NG_VALUE_ACCESSOR",
        "NgModel",
        "ValidationErrors",
        "Validator",
        "noop",
        "Subject",
        "Component",
        "NG_VALUE_ACCESSOR",
        "forwardRef",
        "NumberStepperComponent",
        "NG_VALIDATORS",
        "forwardRef",
        "NumberStepperComponent",
        "ChangeDetectionStrategy",
        "Subject",
        "ViewChild",
        "_",
        "noop",
        "Input",
        "Input",
        "Input",
        "Input",
        "Input",
        "Input",
        "Input",
        "Input",
        "HostBinding",
        "Input",
        "value",
        "value",
        "Input",
        "Input",
        "focus",
        "focus",
        "focus",
        "val",
        "val",
        "val",
        "parsed",
        "parsed",
        "parsed",
        "parsed",
        "val",
        "_decimalPipe",
        "status",
        "status",
        "value",
        "value",
        "fn",
        "_",
        "fn",
        "_fn",
        "_",
        "errors",
        "errors",
        "errors",
        "errors",
        "errors"
    ],
    "literals": [
        "'@angular/common'",
        "'@angular/core'",
        "'@angular/forms'",
        "'rxjs'",
        "'required'",
        "'min'",
        "'max'",
        "'pattern'",
        "'km-number-stepper'",
        "'style.scss'",
        "'template.html'",
        "'input'",
        "string",
        "string",
        "string",
        "'integer'",
        "'decimal'",
        "'integer'",
        "'attr.id'",
        "''",
        "''",
        "string",
        "string",
        "'raw'",
        "'errors'",
        "'hint'",
        "'all'",
        "'raw'",
        "''",
        "''",
        "string",
        "string",
        "string",
        "'decimal'",
        "'1.0-4'",
        "'decimal'",
        "string",
        "'errors'",
        "'all'",
        "string",
        "'integer'",
        "''",
        "'VALID'",
        "${this.label} is required.",
        "Maximum acceptable value is ${this.max}.",
        "Minimum acceptable value is ${this.min}.",
        "'Expected provided number to be an integer.'"
    ],
    "variables": [
        "parsed",
        "errors"
    ],
    "comments": [
        "Copyright 2020 The Kubermatic Kubernetes Platform contributors.",
        "",
        "Licensed under the Apache License, Version 2.0 (the \"License\");",
        "you may not use this file except in compliance with the License.",
        "You may obtain a copy of the License at",
        "",
        "http://www.apache.org/licenses/LICENSE-2.0",
        "",
        "Unless required by applicable law or agreed to in writing, software",
        "distributed under the License is distributed on an \"AS IS\" BASIS,",
        "WITHOUT WARRANTIES OR CONDITIONS OF ANY KIND, either express or implied.",
        "See the License for the specific language governing permissions and",
        "limitations under the License."
    ],
    "docstrings": [
        "* Defines internal behavior of the stepper field.\n   *    raw - all additional error/hint messages will be hidden\n   *    errors - only error message will be shown\n   *    hint - only hint message will be shown\n   *    all - both error and hint messages will be shown"
    ],
    "functions": [
        "id",
        "id",
        "focus",
        "focus",
        "value",
        "value",
        "errors",
        "pattern",
        "ngAfterViewInit",
        "ngOnDestroy",
        "writeValue",
        "registerOnChange",
        "registerOnTouched",
        "validate",
        "onIncrease",
        "onDecrease",
        "_getErrors"
    ],
    "classes": [
        "NumberStepperComponent"
    ]
}