{
    "identifiers": [
        "constants",
        "INPUT_FOR_LOGIN",
        "INPUT_FOR_PASSWORD",
        "LAPTOP",
        "LAPTOPS",
        "TOGETHER_CHEAP",
        "CART_IS_EMPTY",
        "PLAYSTATION",
        "EMPTY_WISH_LIST",
        "BASEURI",
        "KIEV",
        "FIND"
    ],
    "literals": [
        "\"Petrovartem01061996@gmail.com\"",
        "\"01061996Artem\"",
        "\"Ноутбук\"",
        "\"Ноутбуки\"",
        "\"Вместе дешевле\"",
        "\"Корзина пуста\"",
        "\"PlayStation\"",
        "\"У вас еще нет списков желаний\"",
        "\"https://rozetka.com.ua/\"",
        "\"Киев\"",
        "\"Найти\""
    ],
    "variables": [],
    "comments": [],
    "docstrings": [],
    "functions": [
        "Constants"
    ],
    "classes": [
        "Constants"
    ]
}