{
    "identifiers": [
        "require",
        "Deck",
        "arrayFn",
        "arrayFn",
        "arrayFn",
        "Game",
        "selectVector",
        "arrDescriptor",
        "arrDescriptor",
        "Game",
        "selectVector",
        "cards",
        "Deck",
        "requiredCards",
        "cards",
        "i",
        "requiredCards",
        "i",
        "vector",
        "requiredCards",
        "i",
        "numSelected",
        "vector",
        "numSelected",
        "Deck",
        "arrayFn",
        "trialSize",
        "histories",
        "trialSize",
        "i",
        "trialSize",
        "i",
        "arrayFn",
        "game",
        "histories",
        "rating",
        "bestRating",
        "bestGame",
        "game",
        "bestRating",
        "rating",
        "bestGame",
        "Deck",
        "cardName",
        "i",
        "i",
        "i",
        "cardName",
        "i",
        "Deck",
        "game",
        "histories",
        "history",
        "histories",
        "total",
        "total",
        "histories",
        "history",
        "game",
        "len",
        "total",
        "len",
        "Deck",
        "cards",
        "Deck",
        "vector",
        "numSelected",
        "numSelected",
        "vector",
        "vector",
        "index",
        "vector",
        "index",
        "numSelected",
        "vector"
    ],
    "literals": [
        "'./game.js'",
        "'Cellar'",
        "'Action'",
        "'Chapel'",
        "'Action'",
        "'Moat'",
        "'Defense'",
        "'Chancelor'",
        "'Action'",
        "'Village'",
        "'Action'",
        "'Woodcutter'",
        "'Action'",
        "'Workshop'",
        "'Action'",
        "'Bureaucrat'",
        "'Attack'",
        "'Feast'",
        "'Action'",
        "'Gardens'",
        "'Victory'",
        "'Militia'",
        "'Attack'",
        "'Moneylender'",
        "'Action'",
        "'Remodel'",
        "'Action'",
        "'Smithy'",
        "'Action'",
        "'Spy'",
        "'Attack'",
        "'Thief'",
        "'Attack'",
        "'Throne Room'",
        "'Action'",
        "'Council Room'",
        "'Action'",
        "'Festival'",
        "'Action'",
        "'Laboratory'",
        "'Action'",
        "'Library'",
        "'Action'",
        "'Market'",
        "'Action'",
        "'Mine'",
        "'Action'",
        "'Witch'",
        "'Attack'",
        "'Adventurer'",
        "'Action'"
    ],
    "variables": [
        "Game",
        "cards",
        "Deck",
        "arrDescriptor",
        "vector",
        "numSelected",
        "i",
        "games",
        "bestGame",
        "bestRating",
        "i",
        "game",
        "rating",
        "i",
        "total",
        "len",
        "index",
        "found"
    ],
    "comments": [],
    "docstrings": [],
    "functions": [
        "selectVector"
    ],
    "classes": []
}