{
    "identifiers": [
        "Component",
        "BsGridComponent",
        "GridOptions",
        "GridColumn",
        "PersonData",
        "Component",
        "BsGridComponent",
        "GridOptions",
        "GridColumn",
        "GridColumn",
        "PersonData"
    ],
    "literals": [
        "'angular2/core'",
        "'./ng2-bootstrap-grid/ng2-bootstrap-grid'",
        "'./ng2-bootstrap-grid/gridOptions'",
        "'./person'",
        "'app'",
        "'app/app.html'",
        "'app/app.css'",
        "'ID'",
        "'id'",
        "'Name'",
        "'name'",
        "'1'",
        "'Coral'"
    ],
    "variables": [],
    "comments": [],
    "docstrings": [],
    "functions": [],
    "classes": [
        "App"
    ]
}