{
    "identifiers": [
        "require",
        "require",
        "require",
        "require",
        "require",
        "require",
        "express",
        "HttpLink",
        "introspectSchema",
        "wpHttpLink",
        "remoteSchema",
        "makeRemoteExecutableSchema",
        "remoteSchema",
        "wpHttpLink",
        "ApolloServer",
        "schema",
        "InMemoryLRUCache",
        "server",
        "app",
        "port",
        "port"
    ],
    "literals": [
        "'express'",
        "'apollo-server-express'",
        "'apollo-link-http'",
        "'graphql-tools'",
        "'apollo-server-caching'",
        "'isomorphic-fetch'",
        "'http://admin.petertenhoor.nl/graphql'",
        "Proxy is listening on port ${port}"
    ],
    "variables": [
        "express",
        "fetch",
        "port",
        "app",
        "wpHttpLink",
        "remoteSchema",
        "schema",
        "server"
    ],
    "comments": [
        "Start server"
    ],
    "docstrings": [],
    "functions": [],
    "classes": []
}