{
    "identifiers": [
        "safeFetcherWithAuth",
        "TestResult",
        "useQueries",
        "useEffect",
        "useRef",
        "toast",
        "useTestPollingStore",
        "useTestcaseStore",
        "useGetTestResult",
        "useRef",
        "useTestPollingStore",
        "state",
        "state",
        "useTestPollingStore",
        "state",
        "state",
        "getTestResult",
        "safeFetcherWithAuth",
        "baseUrl",
        "res",
        "results",
        "submission",
        "submission",
        "allJudged",
        "setIsTesting",
        "stopPolling",
        "attempts",
        "MAX_ATTEMPTS",
        "attempts",
        "setIsTesting",
        "stopPolling",
        "toast",
        "results",
        "getTestResult",
        "useTestResults",
        "useGetTestResult",
        "useGetTestResult",
        "useTestPollingStore",
        "state",
        "state",
        "useQueries",
        "getSampleTestResult",
        "REFETCH_INTERVAL",
        "samplePollingEnabled",
        "getUserTestResult",
        "REFETCH_INTERVAL",
        "userPollingEnabled",
        "results",
        "results",
        "result",
        "result",
        "results",
        "result",
        "result",
        "useTestcaseStore",
        "state",
        "state",
        "data",
        "testcases",
        "testcase",
        "index",
        "data",
        "item",
        "item",
        "testcase",
        "index",
        "testcase",
        "testcase",
        "testcase",
        "testResult",
        "testResult",
        "testcase",
        "useEffect",
        "isError",
        "toast",
        "setIsTesting",
        "stopPolling",
        "stopPolling",
        "isError",
        "testResults"
    ],
    "literals": [
        "'@/lib/utils'",
        "'@/types/type'",
        "'@tanstack/react-query'",
        "'react'",
        "'sonner'",
        "'../context/TestPollingStoreProvider'",
        "'../context/TestcaseStoreProvider'",
        "'sample'",
        "'user'",
        "'sample'",
        "'submission/test'",
        "'submission/user-test'",
        "'Judging'",
        "'Judging took too long. Please try again later.'",
        "'sample'",
        "'user'",
        "'submittion'",
        "'test'",
        "'submission'",
        "'user-test'",
        "''",
        "''",
        "'Failed to execute some testcases. Please try again later.'",
        "'sample'",
        "'user'"
    ],
    "variables": [
        "MAX_ATTEMPTS",
        "REFETCH_INTERVAL",
        "useGetTestResult",
        "attempts",
        "setIsTesting",
        "stopPolling",
        "baseUrl",
        "getTestResult",
        "res",
        "results",
        "allJudged",
        "useTestResults",
        "getSampleTestResult",
        "getUserTestResult",
        "testcases",
        "testResults",
        "testResult"
    ],
    "comments": [
        "Test execution is finished",
        "Retry",
        "No more retry"
    ],
    "docstrings": [],
    "functions": [],
    "classes": []
}