{
    "identifiers": [
        "java",
        "util",
        "Scanner",
        "title",
        "author",
        "price",
        "title",
        "author",
        "price",
        "title",
        "title",
        "author",
        "author",
        "price",
        "price",
        "title",
        "author",
        "price",
        "title",
        "author",
        "price",
        "args",
        "scanner",
        "books",
        "i",
        "i",
        "i",
        "i",
        "title",
        "scanner",
        "nextLine",
        "author",
        "scanner",
        "nextLine",
        "price",
        "scanner",
        "nextDouble",
        "scanner",
        "nextLine",
        "books",
        "i",
        "title",
        "author",
        "price",
        "searchTitle",
        "scanner",
        "nextLine",
        "found",
        "book",
        "books",
        "book",
        "getTitle",
        "equalsIgnoreCase",
        "searchTitle",
        "book",
        "displayBookDetails",
        "found",
        "found"
    ],
    "literals": [
        "\"Title: \"",
        "\"Author: \"",
        "\"Price: \"",
        "\"Enter details for Book \"",
        "\":\"",
        "\"Enter Book Title: \"",
        "\"Enter Book Author: \"",
        "\"Enter Book Price: \"",
        "\"Enter the title of the book you want to search for: \"",
        "\"\\nBook Found!\"",
        "\"Book not found!\""
    ],
    "variables": [
        "title",
        "author",
        "price"
    ],
    "comments": [],
    "docstrings": [],
    "functions": [
        "Book",
        "getTitle",
        "getAuthor",
        "getPrice",
        "displayBookDetails",
        "main"
    ],
    "classes": [
        "Book",
        "LibraryBookManagement"
    ]
}