{
    "identifiers": [
        "React",
        "ReactDOM",
        "SizedPlayer",
        "parseAspectRatio",
        "describe",
        "it",
        "ReactDOM",
        "SizedPlayer",
        "div",
        "it",
        "expect",
        "parseAspectRatio",
        "expect",
        "parseAspectRatio",
        "expect",
        "parseAspectRatio"
    ],
    "literals": [
        "'react'",
        "'react-dom'",
        "'../SizedPlayer'",
        "'<SizedPlayer />'",
        "'renders without crashing'",
        "'div'",
        "\"video.mp4\"",
        "'it parses aspect ratios correctly'",
        "'1:2'",
        "'1:2:3'",
        "'foobar'"
    ],
    "variables": [
        "div"
    ],
    "comments": [],
    "docstrings": [],
    "functions": [],
    "classes": []
}